{
  "高压输入": "../static/device_icons/高压输入.png",
  "高压柜": "../static/device_icons/高压柜.png",
  "变压器": "../static/device_icons/变压器.png",
  "低压柜": "../static/device_icons/低压柜.png",
  "变压器联络互联": "../static/device_icons/变压器联络互联.png",
  "油机": "../static/device_icons/油机.png",
  "油机输出屏": "../static/device_icons/油机输出屏.png",
  "油机联络柜": "../static/device_icons/油机联络柜.png",
  "油机直供屏": "../static/device_icons/油机直供屏.png",
  "低压配电屏": "../static/device_icons/低压配电屏.png",
  "电池组": "../static/device_icons/电池组.png",
  "整流系统": "../static/device_icons/整流系统.png",
  "UPS": "../static/device_icons/ups.png",
  "机房": "../static/device_icons/机房.png",
  "微模块": "../static/device_icons/微模块.png",
  "空调": "../static/device_icons/空调.png",
  "配电箱": "../static/device_icons/配电箱.png"
}